MSDTransformer.py
__init__.py
setup.py
utils/max_std_calculator_gurobi.py
utils/max_std_calculator_scip.py
wmsd-1.0.0.dist-info/LICENSE
wmsd-1.0.0.dist-info/METADATA
wmsd-1.0.0.dist-info/WHEEL
wmsd-1.0.0.dist-info/top_level.txt
wmsd-1.0.0.dist-info/RECORD
