Metadata-Version: 2.1
Name: wmsd
Version: 1.0.0
Summary: TOPSIS ranking and interpretation using WMSD-space
Author-email: Maciej Woś <maciejwos01@gmail.com>, Bogna Kilanowska <bogna.kilanowska@student.put.poznan.pl>, Adam Ciesiółka <adam.ciesiolka@student.put.poznan.pl>
License: MIT License
Project-URL: repository, https://github.com/dabrze/topsis-msd-improvement-actions
Keywords: visualization,ranking,multi-criteria-decision-aid,mcda,topsis,explainability
Classifier: License :: OSI Approved :: MIT License
Classifier: Programming Language :: Python :: 3
Classifier: Operating System :: OS Independent
Requires-Python: >=3.9
License-File: LICENSE
Requires-Dist: dataclasses
Requires-Dist: jupyter
Requires-Dist: numpy ==1.26.0
Requires-Dist: pandas ~=1.5
Requires-Dist: scikit-learn ==1.3.0
Requires-Dist: matplotlib ==3.8.0
Requires-Dist: plotly ==5.17.0
Requires-Dist: pytest ==7.4.2
Requires-Dist: ipython ==8.15.0
Requires-Dist: pymoo ~=0.6.0
Requires-Dist: pyscipopt
Requires-Dist: sphinx ==7.1.2
Requires-Dist: sphinx-rtd-theme ==1.3.0rc1
Requires-Dist: nbformat
